cproj.py
cproj-1.0.1.dist-info/METADATA
cproj-1.0.1.dist-info/metadata.json
cproj-1.0.1.dist-info/entry_points.txt
cproj-1.0.1.dist-info/top_level.txt
cproj-1.0.1.dist-info/DESCRIPTION.rst
cproj-1.0.1.dist-info/WHEEL
cproj-1.0.1.dist-info/RECORD
