Metadata-Version: 2.0
Name: cproj
Version: 1.0.1
Summary: A simple project template generator for C and C++
Home-page: https://github.com/vitrig/cproj
Author: Przemysław Czarnota
Author-email: x2n404@gmail.com
License: MIT
Keywords: cproj project generator template
Platform: UNKNOWN
Classifier: Development Status :: 3 - Alpha
Classifier: Intended Audience :: Developers
Classifier: Topic :: Software Development :: Code Generators
Classifier: License :: OSI Approved :: MIT License
Classifier: Programming Language :: Python :: 3
Classifier: Programming Language :: Python :: 3.2
Classifier: Programming Language :: Python :: 3.3
Classifier: Programming Language :: Python :: 3.4
Classifier: Programming Language :: Python :: 3.5
